{"class": [{"method": "get", "url": "/class", "queryParams": [], "bodyParams": [], "response": {"Address": "str", "Class_ID": "int", "School_Has_CST_No": "int", "Teacher_Takes_Teacher_ID": "int"}, "ui_name": "get_class", "cluster_name": "class", "endpoint_name": "get_class", "is_single_entity": true}, {"method": "post", "url": "/class", "queryParams": [], "bodyParams": [["Address", "str"], ["Class_ID", "int"], ["School_Has_CST_No", "int"], ["Teacher_Takes_Teacher_ID", "int"]], "response": {"Address": "str", "Class_ID": "int", "School_Has_CST_No": "int", "Teacher_Takes_Teacher_ID": "int"}, "ui_name": "create_class", "cluster_name": "class", "endpoint_name": "create_class", "is_single_entity": true}], "time_table": [{"method": "get", "url": "/time_table", "queryParams": [], "bodyParams": [], "response": {"Subject_ID": "str", "Class_ID": "int", "Period_ID": "int", "Organizes": "str", "Class_Has_Class_ID": "int"}, "ui_name": "get_time_table", "cluster_name": "time_table", "endpoint_name": "get_time_table", "is_single_entity": true}, {"method": "post", "url": "/time_table", "queryParams": [], "bodyParams": [["Subject_ID", "str"], ["Class_ID", "int"], ["Period_ID", "int"], ["Organizes", "str"], ["Class_Has_Class_ID", "int"]], "response": {"Subject_ID": "str", "Class_ID": "int", "Period_ID": "int", "Organizes": "str", "Class_Has_Class_ID": "int"}, "ui_name": "create_time_table", "cluster_name": "time_table", "endpoint_name": "create_time_table", "is_single_entity": true}], "examination": [{"method": "get", "url": "/examination", "queryParams": [], "bodyParams": [], "response": {"Subject_ID": "str", "Exam_ID": "int", "Date": "datetime"}, "ui_name": "get_examination", "cluster_name": "examination", "endpoint_name": "get_examination", "is_single_entity": true}, {"method": "post", "url": "/examination", "queryParams": [], "bodyParams": [["Subject_ID", "str"], ["Exam_ID", "int"], ["Date", "datetime"]], "response": {"Subject_ID": "str", "Exam_ID": "int", "Date": "datetime"}, "ui_name": "create_examination", "cluster_name": "examination", "endpoint_name": "create_examination", "is_single_entity": true}], "teacher": [{"method": "get", "url": "/teacher", "queryParams": [], "bodyParams": [], "response": {"Address": "str", "attr_2": "str", "Teacher_ID": "int"}, "ui_name": "get_teacher", "cluster_name": "teacher", "endpoint_name": "get_teacher", "is_single_entity": true}, {"method": "post", "url": "/teacher", "queryParams": [], "bodyParams": [["Address", "str"], ["attr_2", "str"], ["Teacher_ID", "int"]], "response": {"Address": "str", "attr_2": "str", "Teacher_ID": "int"}, "ui_name": "create_teacher", "cluster_name": "teacher", "endpoint_name": "create_teacher", "is_single_entity": true}], "subject": [{"method": "get", "url": "/subject", "queryParams": [], "bodyParams": [], "response": {"IncrementalKey": "int", "Teacher_Has_Teacher_ID": "int"}, "ui_name": "get_subject", "cluster_name": "subject", "endpoint_name": "get_subject", "is_single_entity": true}, {"method": "post", "url": "/subject", "queryParams": [], "bodyParams": [["IncrementalKey", "int"], ["Teacher_Has_Teacher_ID", "int"]], "response": {"IncrementalKey": "int", "Teacher_Has_Teacher_ID": "int"}, "ui_name": "create_subject", "cluster_name": "subject", "endpoint_name": "create_subject", "is_single_entity": true}], "student": [{"method": "get", "url": "/student", "queryParams": [], "bodyParams": [], "response": {"attr_1": "str", "Address": "str", "Student_ID": "int", "School_Has_CST_No": "int"}, "ui_name": "get_student", "cluster_name": "student", "endpoint_name": "get_student", "is_single_entity": true}, {"method": "post", "url": "/student", "queryParams": [], "bodyParams": [["attr_1", "str"], ["Address", "str"], ["Student_ID", "int"], ["School_Has_CST_No", "int"]], "response": {"attr_1": "str", "Address": "str", "Student_ID": "int", "School_Has_CST_No": "int"}, "ui_name": "create_student", "cluster_name": "student", "endpoint_name": "create_student", "is_single_entity": true}], "student_ee": [{"method": "get", "url": "/student_ee", "queryParams": [], "bodyParams": [], "response": {"ee": "str", "Student_Student_ID": "int"}, "ui_name": "get_student_ee", "cluster_name": "student_ee", "endpoint_name": "get_student_ee", "is_single_entity": true}, {"method": "post", "url": "/student_ee", "queryParams": [], "bodyParams": [["ee", "str"], ["Student_Student_ID", "int"]], "response": {"ee": "str", "Student_Student_ID": "int"}, "ui_name": "create_student_ee", "cluster_name": "student_ee", "endpoint_name": "create_student_ee", "is_single_entity": true}], "employee": [{"method": "get", "url": "/employee", "queryParams": [], "bodyParams": [], "response": {"Employee_ID": "int", "attr_3": "str", "Teacher_IsA_Teacher_ID": "int"}, "ui_name": "get_employee", "cluster_name": "employee", "endpoint_name": "get_employee", "is_single_entity": true}, {"method": "post", "url": "/employee", "queryParams": [], "bodyParams": [["Employee_ID", "int"], ["attr_3", "str"], ["Teacher_IsA_Teacher_ID", "int"]], "response": {"Employee_ID": "int", "attr_3": "str", "Teacher_IsA_Teacher_ID": "int"}, "ui_name": "create_employee", "cluster_name": "employee", "endpoint_name": "create_employee", "is_single_entity": true}], "school": [{"method": "get", "url": "/school", "queryParams": [], "bodyParams": [], "response": {"attr_4": "str", "Address": "str", "CST_No": "int"}, "ui_name": "get_school", "cluster_name": "school", "endpoint_name": "get_school", "is_single_entity": true}, {"method": "post", "url": "/school", "queryParams": [], "bodyParams": [["attr_4", "str"], ["Address", "str"], ["CST_No", "int"]], "response": {"attr_4": "str", "Address": "str", "CST_No": "int"}, "ui_name": "create_school", "cluster_name": "school", "endpoint_name": "create_school", "is_single_entity": true}], "supplier": [{"method": "get", "url": "/supplier", "queryParams": [], "bodyParams": [], "response": {"attr_5": "str", "Address": "str", "Pub_ID": "str", "Supplied_by": "datetime"}, "ui_name": "get_supplier", "cluster_name": "supplier", "endpoint_name": "get_supplier", "is_single_entity": true}, {"method": "post", "url": "/supplier", "queryParams": [], "bodyParams": [["attr_5", "str"], ["Address", "str"], ["Pub_ID", "str"], ["Supplied_by", "datetime"]], "response": {"attr_5": "str", "Address": "str", "Pub_ID": "str", "Supplied_by": "datetime"}, "ui_name": "create_supplier", "cluster_name": "supplier", "endpoint_name": "create_supplier", "is_single_entity": true}], "supplier_ee": [{"method": "get", "url": "/supplier_ee", "queryParams": [], "bodyParams": [], "response": {"ee": "str", "Supplier_Pub_ID": "str"}, "ui_name": "get_supplier_ee", "cluster_name": "supplier_ee", "endpoint_name": "get_supplier_ee", "is_single_entity": true}, {"method": "post", "url": "/supplier_ee", "queryParams": [], "bodyParams": [["ee", "str"], ["Supplier_Pub_ID", "str"]], "response": {"ee": "str", "Supplier_Pub_ID": "str"}, "ui_name": "create_supplier_ee", "cluster_name": "supplier_ee", "endpoint_name": "create_supplier_ee", "is_single_entity": true}], "library": [{"method": "get", "url": "/library", "queryParams": [], "bodyParams": [], "response": {"Address": "str", "attr_7": "str", "School_Has_CST_No": "int"}, "ui_name": "get_library", "cluster_name": "library", "endpoint_name": "get_library", "is_single_entity": true}, {"method": "post", "url": "/library", "queryParams": [], "bodyParams": [["Address", "str"], ["attr_7", "str"], ["School_Has_CST_No", "int"]], "response": {"Address": "str", "attr_7": "str", "School_Has_CST_No": "int"}, "ui_name": "create_library", "cluster_name": "library", "endpoint_name": "create_library", "is_single_entity": true}], "member": [{"method": "get", "url": "/member", "queryParams": [], "bodyParams": [], "response": {"attr_6": "str", "Address": "str", "Member_ID": "int"}, "ui_name": "get_member", "cluster_name": "member", "endpoint_name": "get_member", "is_single_entity": true}, {"method": "post", "url": "/member", "queryParams": [], "bodyParams": [["attr_6", "str"], ["Address", "str"], ["Member_ID", "int"]], "response": {"attr_6": "str", "Address": "str", "Member_ID": "int"}, "ui_name": "create_member", "cluster_name": "member", "endpoint_name": "create_member", "is_single_entity": true}], "publisher": [{"method": "get", "url": "/publisher", "queryParams": [], "bodyParams": [], "response": {"attr_8": "str", "Pub_ID": "str", "Address": "str"}, "ui_name": "get_publisher", "cluster_name": "publisher", "endpoint_name": "get_publisher", "is_single_entity": true}, {"method": "post", "url": "/publisher", "queryParams": [], "bodyParams": [["attr_8", "str"], ["Pub_ID", "str"], ["Address", "str"]], "response": {"attr_8": "str", "Pub_ID": "str", "Address": "str"}, "ui_name": "create_publisher", "cluster_name": "publisher", "endpoint_name": "create_publisher", "is_single_entity": true}], "publisher_ee": [{"method": "get", "url": "/publisher_ee", "queryParams": [], "bodyParams": [], "response": {"ee": "str", "Publisher_Pub_ID": "str"}, "ui_name": "get_publisher_ee", "cluster_name": "publisher_ee", "endpoint_name": "get_publisher_ee", "is_single_entity": true}, {"method": "post", "url": "/publisher_ee", "queryParams": [], "bodyParams": [["ee", "str"], ["Publisher_Pub_ID", "str"]], "response": {"ee": "str", "Publisher_Pub_ID": "str"}, "ui_name": "create_publisher_ee", "cluster_name": "publisher_ee", "endpoint_name": "create_publisher_ee", "is_single_entity": true}], "book": [{"method": "get", "url": "/book", "queryParams": [], "bodyParams": [], "response": {"Book_ID": "int", "Charge": "str", "attr_9": "str", "Library_Has_attr_7": "str", "Return_Date": "str", "Member_Issued_To_Member_ID": "int", "Publisher_Published_by_Pub_ID": "str"}, "ui_name": "get_book", "cluster_name": "book", "endpoint_name": "get_book", "is_single_entity": true}, {"method": "post", "url": "/book", "queryParams": [], "bodyParams": [["Book_ID", "int"], ["Charge", "str"], ["attr_9", "str"], ["Library_Has_attr_7", "str"], ["Return_Date", "str"], ["Member_Issued_To_Member_ID", "int"], ["Publisher_Published_by_Pub_ID", "str"]], "response": {"Book_ID": "int", "Charge": "str", "attr_9": "str", "Library_Has_attr_7": "str", "Return_Date": "str", "Member_Issued_To_Member_ID": "int", "Publisher_Published_by_Pub_ID": "str"}, "ui_name": "create_book", "cluster_name": "book", "endpoint_name": "create_book", "is_single_entity": true}], "enroll_class_examination": [{"method": "get", "url": "/enroll_class_examination", "queryParams": [], "bodyParams": [], "response": {"Enrollment_Date": "int", "Class_Class_ID": "int", "Examination_Subject_ID": "str", "Examination_Exam_ID": "int"}, "ui_name": "get_enroll_class_examination", "cluster_name": "enroll_class_examination", "endpoint_name": "get_enroll_class_examination", "is_single_entity": true}, {"method": "post", "url": "/enroll_class_examination", "queryParams": [], "bodyParams": [["Enrollment_Date", "int"], ["Class_Class_ID", "int"], ["Examination_Subject_ID", "str"], ["Examination_Exam_ID", "int"]], "response": {"Enrollment_Date": "int", "Class_Class_ID": "int", "Examination_Subject_ID": "str", "Examination_Exam_ID": "int"}, "ui_name": "create_enroll_class_examination", "cluster_name": "enroll_class_examination", "endpoint_name": "create_enroll_class_examination", "is_single_entity": true}], "reads_subject_student": [{"method": "get", "url": "/reads_subject_student", "queryParams": [], "bodyParams": [], "response": {"Subject_IncrementalKey": "int", "Student_Student_ID": "int"}, "ui_name": "get_reads_subject_student", "cluster_name": "reads_subject_student", "endpoint_name": "get_reads_subject_student", "is_single_entity": true}, {"method": "post", "url": "/reads_subject_student", "queryParams": [], "bodyParams": [["Subject_IncrementalKey", "int"], ["Student_Student_ID", "int"]], "response": {"Subject_IncrementalKey": "int", "Student_Student_ID": "int"}, "ui_name": "create_reads_subject_student", "cluster_name": "reads_subject_student", "endpoint_name": "create_reads_subject_student", "is_single_entity": true}], "has_subject_school": [{"method": "get", "url": "/has_subject_school", "queryParams": [], "bodyParams": [], "response": {"Subject_IncrementalKey": "int", "School_CST_No": "int"}, "ui_name": "get_has_subject_school", "cluster_name": "has_subject_school", "endpoint_name": "get_has_subject_school", "is_single_entity": true}, {"method": "post", "url": "/has_subject_school", "queryParams": [], "bodyParams": [["Subject_IncrementalKey", "int"], ["School_CST_No", "int"]], "response": {"Subject_IncrementalKey": "int", "School_CST_No": "int"}, "ui_name": "create_has_subject_school", "cluster_name": "has_subject_school", "endpoint_name": "create_has_subject_school", "is_single_entity": true}], "has_employee_school": [{"method": "get", "url": "/has_employee_school", "queryParams": [], "bodyParams": [], "response": {"Employee_Employee_ID": "int", "School_CST_No": "int"}, "ui_name": "get_has_employee_school", "cluster_name": "has_employee_school", "endpoint_name": "get_has_employee_school", "is_single_entity": true}, {"method": "post", "url": "/has_employee_school", "queryParams": [], "bodyParams": [["Employee_Employee_ID", "int"], ["School_CST_No", "int"]], "response": {"Employee_Employee_ID": "int", "School_CST_No": "int"}, "ui_name": "create_has_employee_school", "cluster_name": "has_employee_school", "endpoint_name": "create_has_employee_school", "is_single_entity": true}], "has_library_member": [{"method": "get", "url": "/has_library_member", "queryParams": [], "bodyParams": [], "response": {"Library_attr_7": "str", "Member_Member_ID": "int"}, "ui_name": "get_has_library_member", "cluster_name": "has_library_member", "endpoint_name": "get_has_library_member", "is_single_entity": true}, {"method": "post", "url": "/has_library_member", "queryParams": [], "bodyParams": [["Library_attr_7", "str"], ["Member_Member_ID", "int"]], "response": {"Library_attr_7": "str", "Member_Member_ID": "int"}, "ui_name": "create_has_library_member", "cluster_name": "has_library_member", "endpoint_name": "create_has_library_member", "is_single_entity": true}]}
